__init__.py
__main__.py
bulk_rename.py
BulkRenamerPy-0.1.5.dist-info/LICENSE
BulkRenamerPy-0.1.5.dist-info/METADATA
BulkRenamerPy-0.1.5.dist-info/WHEEL
BulkRenamerPy-0.1.5.dist-info/entry_points.txt
BulkRenamerPy-0.1.5.dist-info/top_level.txt
BulkRenamerPy-0.1.5.dist-info/RECORD
