Metadata-Version: 2.1
Name: BulkRenamerPy
Version: 0.1.5
Summary: A simple tool to bulk rename files in a directory
Author-email: Bruno Anesio <brunohanesio@gmail.com>
Project-URL: Homepage, https://github.com/brunoanesio/bulk-rename
Project-URL: Bug Tracker, https://github.com/brunoanesio/bulk-rename/issues
Keywords: bulk rename,rename,rename files
Classifier: Programming Language :: Python :: 3
Classifier: License :: OSI Approved :: GNU General Public License v3 (GPLv3)
Classifier: Operating System :: OS Independent
Requires-Python: >=3.8
License-File: LICENSE
Requires-Dist: click
Requires-Dist: markdown
Requires-Dist: mdurl
Requires-Dist: packaging
Requires-Dist: Pygments
Requires-Dist: rich
Requires-Dist: rich-click
Provides-Extra: test
Requires-Dist: pytest ; extra == 'test'
